{
  "source": {
    "title": "Eldervale Seed Story",
    "text": "Deep within the mist‑soaked kingdom of Eldervale, a young mage named Liora discovered a silver seed glowing at the heart of an abandoned forest temple. Legends whispered that such seeds held the last remnants of ancient star‑spirits, long thought lost to time. When Liora touched it, the seed burst into swirling constellations that wrapped around her like living light, revealing a hidden path through the trees. Drawn forward, she followed the shimmering trail to a forgotten citadel suspended in the sky, its towers humming with dormant magic. As she stepped inside, the constellations settled into her palms, forming runes that pulsed with power—signaling that she had been chosen to awaken the citadel and restore the balance between the mortal world and the fading realm of stars."
  },
  "entities": [
    {
      "id": "ent_000001",
      "entityType": "location",
      "name": "Eldervale",
      "aliases": [],
      "facts": [
        {
          "key": "description",
          "value": "A mist‑soaked fantasy kingdom.",
          "time": "t_000"
        }
      ],
      "version": 1
    },
    {
      "id": "ent_000002",
      "entityType": "character",
      "name": "Liora",
      "aliases": [],
      "facts": [
        {
          "key": "description",
          "value": "A young mage who discovers the silver seed.",
          "time": "t_000"
        }
      ],
      "version": 1
    },
    {
      "id": "ent_000003",
      "entityType": "object",
      "name": "Silver seed",
      "aliases": ["silver seed"],
      "facts": [
        {
          "key": "description",
          "value": "A glowing seed containing remnants of star‑spirits.",
          "time": "t_000"
        }
      ],
      "version": 1
    },
    {
      "id": "ent_000004",
      "entityType": "location",
      "name": "Ancient forest temple",
      "aliases": ["abandoned forest temple"],
      "facts": [
        {
          "key": "description",
          "value": "An abandoned temple deep in the forest where the seed is found.",
          "time": "t_000"
        }
      ],
      "version": 1
    },
    {
      "id": "ent_000005",
      "entityType": "character",
      "name": "Star‑spirits",
      "aliases": ["star spirits"],
      "facts": [
        {
          "key": "description",
          "value": "Ancient celestial beings whose remnants live inside the seed.",
          "time": "t_000"
        }
      ],
      "version": 1
    },
    {
      "id": "ent_000006",
      "entityType": "concept",
      "name": "Constellations",
      "aliases": [],
      "facts": [
        {
          "key": "description",
          "value": "Living, swirling star‑patterns released from the seed.",
          "time": "t_000"
        }
      ],
      "version": 1
    },
    {
      "id": "ent_000007",
      "entityType": "location",
      "name": "Hidden path",
      "aliases": [],
      "facts": [
        {
          "key": "description",
          "value": "A secret route revealed by the constellations.",
          "time": "t_000"
        }
      ],
      "version": 1
    },
    {
      "id": "ent_000008",
      "entityType": "location",
      "name": "Forgotten citadel",
      "aliases": [],
      "facts": [
        {
          "key": "description",
          "value": "A sky‑suspended citadel with dormant magic.",
          "time": "t_000"
        }
      ],
      "version": 1
    },
    {
      "id": "ent_000009",
      "entityType": "location",
      "name": "Sky‑suspended towers",
      "aliases": ["towers"],
      "facts": [
        {
          "key": "description",
          "value": "Part of the citadel, humming with magic.",
          "time": "t_000"
        }
      ],
      "version": 1
    },
    {
      "id": "ent_000010",
      "entityType": "object",
      "name": "Runes",
      "aliases": [],
      "facts": [
        {
          "key": "description",
          "value": "Symbols of power that form in Liora’s palms.",
          "time": "t_000"
        }
      ],
      "version": 1
    },
    {
      "id": "ent_000011",
      "entityType": "location",
      "name": "Realm of stars",
      "aliases": ["fading realm of stars"],
      "facts": [
        {
          "key": "description",
          "value": "A fading celestial realm Liora is destined to help restore.",
          "time": "t_000"
        }
      ],
      "version": 1
    }
  ]
}
